README.md
setup.py
mycroft_plugin_silero/__init__.py
mycroft_plugin_silero/tts.py
mycroft_plugin_silero.egg-info/PKG-INFO
mycroft_plugin_silero.egg-info/SOURCES.txt
mycroft_plugin_silero.egg-info/dependency_links.txt
mycroft_plugin_silero.egg-info/entry_points.txt
mycroft_plugin_silero.egg-info/requires.txt
mycroft_plugin_silero.egg-info/top_level.txt
mycroft_plugin_silero.egg-info/zip-safe